{"nodes": [{"id": "c_users_anton_documents_projects_formflow_formflow_src_app_api_submissions_route_ts", "label": "route.ts", "file_type": "code", "source_file": "C:\\Users\\anton\\Documents\\Projects\\formflow\\formflow\\src\\app\\api\\submissions\\route.ts", "source_location": "L1"}, {"id": "route_get", "label": "GET()", "file_type": "code", "source_file": "C:\\Users\\anton\\Documents\\Projects\\formflow\\formflow\\src\\app\\api\\submissions\\route.ts", "source_location": "L13"}, {"id": "route_post", "label": "POST()", "file_type": "code", "source_file": "C:\\Users\\anton\\Documents\\Projects\\formflow\\formflow\\src\\app\\api\\submissions\\route.ts", "source_location": "L74"}], "edges": [{"source": "c_users_anton_documents_projects_formflow_formflow_src_app_api_submissions_route_ts", "target": "db", "relation": "imports_from", "confidence": "EXTRACTED", "source_file": "C:\\Users\\anton\\Documents\\Projects\\formflow\\formflow\\src\\app\\api\\submissions\\route.ts", "source_location": "L1", "weight": 1.0}, {"source": "c_users_anton_documents_projects_formflow_formflow_src_app_api_submissions_route_ts", "target": "errors", "relation": "imports_from", "confidence": "EXTRACTED", "source_file": "C:\\Users\\anton\\Documents\\Projects\\formflow\\formflow\\src\\app\\api\\submissions\\route.ts", "source_location": "L2", "weight": 1.0}, {"source": "c_users_anton_documents_projects_formflow_formflow_src_app_api_submissions_route_ts", "target": "audit", "relation": "imports_from", "confidence": "EXTRACTED", "source_file": "C:\\Users\\anton\\Documents\\Projects\\formflow\\formflow\\src\\app\\api\\submissions\\route.ts", "source_location": "L3", "weight": 1.0}, {"source": "c_users_anton_documents_projects_formflow_formflow_src_app_api_submissions_route_ts", "target": "field_access", "relation": "imports_from", "confidence": "EXTRACTED", "source_file": "C:\\Users\\anton\\Documents\\Projects\\formflow\\formflow\\src\\app\\api\\submissions\\route.ts", "source_location": "L4", "weight": 1.0}, {"source": "c_users_anton_documents_projects_formflow_formflow_src_app_api_submissions_route_ts", "target": "permissions", "relation": "imports_from", "confidence": "EXTRACTED", "source_file": "C:\\Users\\anton\\Documents\\Projects\\formflow\\formflow\\src\\app\\api\\submissions\\route.ts", "source_location": "L5", "weight": 1.0}, {"source": "c_users_anton_documents_projects_formflow_formflow_src_app_api_submissions_route_ts", "target": "submission_encryption", "relation": "imports_from", "confidence": "EXTRACTED", "source_file": "C:\\Users\\anton\\Documents\\Projects\\formflow\\formflow\\src\\app\\api\\submissions\\route.ts", "source_location": "L6", "weight": 1.0}, {"source": "c_users_anton_documents_projects_formflow_formflow_src_app_api_submissions_route_ts", "target": "submission_visibility", "relation": "imports_from", "confidence": "EXTRACTED", "source_file": "C:\\Users\\anton\\Documents\\Projects\\formflow\\formflow\\src\\app\\api\\submissions\\route.ts", "source_location": "L7", "weight": 1.0}, {"source": "c_users_anton_documents_projects_formflow_formflow_src_app_api_submissions_route_ts", "target": "temporal", "relation": "imports_from", "confidence": "EXTRACTED", "source_file": "C:\\Users\\anton\\Documents\\Projects\\formflow\\formflow\\src\\app\\api\\submissions\\route.ts", "source_location": "L8", "weight": 1.0}, {"source": "c_users_anton_documents_projects_formflow_formflow_src_app_api_submissions_route_ts", "target": "submissions", "relation": "imports_from", "confidence": "EXTRACTED", "source_file": "C:\\Users\\anton\\Documents\\Projects\\formflow\\formflow\\src\\app\\api\\submissions\\route.ts", "source_location": "L9", "weight": 1.0}, {"source": "c_users_anton_documents_projects_formflow_formflow_src_app_api_submissions_route_ts", "target": "formio_sensitive_fields", "relation": "imports_from", "confidence": "EXTRACTED", "source_file": "C:\\Users\\anton\\Documents\\Projects\\formflow\\formflow\\src\\app\\api\\submissions\\route.ts", "source_location": "L10", "weight": 1.0}, {"source": "c_users_anton_documents_projects_formflow_formflow_src_app_api_submissions_route_ts", "target": "approvalworkflow", "relation": "imports_from", "confidence": "EXTRACTED", "source_file": "C:\\Users\\anton\\Documents\\Projects\\formflow\\formflow\\src\\app\\api\\submissions\\route.ts", "source_location": "L11", "weight": 1.0}, {"source": "c_users_anton_documents_projects_formflow_formflow_src_app_api_submissions_route_ts", "target": "route_get", "relation": "contains", "confidence": "EXTRACTED", "source_file": "C:\\Users\\anton\\Documents\\Projects\\formflow\\formflow\\src\\app\\api\\submissions\\route.ts", "source_location": "L13", "weight": 1.0}, {"source": "c_users_anton_documents_projects_formflow_formflow_src_app_api_submissions_route_ts", "target": "route_post", "relation": "contains", "confidence": "EXTRACTED", "source_file": "C:\\Users\\anton\\Documents\\Projects\\formflow\\formflow\\src\\app\\api\\submissions\\route.ts", "source_location": "L74", "weight": 1.0}], "raw_calls": [{"caller_nid": "route_get", "callee": "requireUser", "source_file": "C:\\Users\\anton\\Documents\\Projects\\formflow\\formflow\\src\\app\\api\\submissions\\route.ts", "source_location": "L15"}, {"caller_nid": "route_get", "callee": "findMany", "source_file": "C:\\Users\\anton\\Documents\\Projects\\formflow\\formflow\\src\\app\\api\\submissions\\route.ts", "source_location": "L17"}, {"caller_nid": "route_get", "callee": "submissionVisibilityWhere", "source_file": "C:\\Users\\anton\\Documents\\Projects\\formflow\\formflow\\src\\app\\api\\submissions\\route.ts", "source_location": "L18"}, {"caller_nid": "route_get", "callee": "all", "source_file": "C:\\Users\\anton\\Documents\\Projects\\formflow\\formflow\\src\\app\\api\\submissions\\route.ts", "source_location": "L26"}, {"caller_nid": "route_get", "callee": "flatMap", "source_file": "C:\\Users\\anton\\Documents\\Projects\\formflow\\formflow\\src\\app\\api\\submissions\\route.ts", "source_location": "L27"}, {"caller_nid": "route_get", "callee": "map", "source_file": "C:\\Users\\anton\\Documents\\Projects\\formflow\\formflow\\src\\app\\api\\submissions\\route.ts", "source_location": "L58"}, {"caller_nid": "route_get", "callee": "json", "source_file": "C:\\Users\\anton\\Documents\\Projects\\formflow\\formflow\\src\\app\\api\\submissions\\route.ts", "source_location": "L68"}, {"caller_nid": "route_get", "callee": "apiErrorResponse", "source_file": "C:\\Users\\anton\\Documents\\Projects\\formflow\\formflow\\src\\app\\api\\submissions\\route.ts", "source_location": "L70"}, {"caller_nid": "route_post", "callee": "requireUser", "source_file": "C:\\Users\\anton\\Documents\\Projects\\formflow\\formflow\\src\\app\\api\\submissions\\route.ts", "source_location": "L76"}, {"caller_nid": "route_post", "callee": "json", "source_file": "C:\\Users\\anton\\Documents\\Projects\\formflow\\formflow\\src\\app\\api\\submissions\\route.ts", "source_location": "L77"}, {"caller_nid": "route_post", "callee": "parse", "source_file": "C:\\Users\\anton\\Documents\\Projects\\formflow\\formflow\\src\\app\\api\\submissions\\route.ts", "source_location": "L78"}, {"caller_nid": "route_post", "callee": "findUnique", "source_file": "C:\\Users\\anton\\Documents\\Projects\\formflow\\formflow\\src\\app\\api\\submissions\\route.ts", "source_location": "L80"}, {"caller_nid": "route_post", "callee": "encryptSensitiveSubmissionData", "source_file": "C:\\Users\\anton\\Documents\\Projects\\formflow\\formflow\\src\\app\\api\\submissions\\route.ts", "source_location": "L89"}, {"caller_nid": "route_post", "callee": "create", "source_file": "C:\\Users\\anton\\Documents\\Projects\\formflow\\formflow\\src\\app\\api\\submissions\\route.ts", "source_location": "L94"}, {"caller_nid": "route_post", "callee": "getTemporalClient", "source_file": "C:\\Users\\anton\\Documents\\Projects\\formflow\\formflow\\src\\app\\api\\submissions\\route.ts", "source_location": "L114"}, {"caller_nid": "route_post", "callee": "start", "source_file": "C:\\Users\\anton\\Documents\\Projects\\formflow\\formflow\\src\\app\\api\\submissions\\route.ts", "source_location": "L116"}, {"caller_nid": "route_post", "callee": "update", "source_file": "C:\\Users\\anton\\Documents\\Projects\\formflow\\formflow\\src\\app\\api\\submissions\\route.ts", "source_location": "L129"}, {"caller_nid": "route_post", "callee": "writeAuditLog", "source_file": "C:\\Users\\anton\\Documents\\Projects\\formflow\\formflow\\src\\app\\api\\submissions\\route.ts", "source_location": "L137"}, {"caller_nid": "route_post", "callee": "json", "source_file": "C:\\Users\\anton\\Documents\\Projects\\formflow\\formflow\\src\\app\\api\\submissions\\route.ts", "source_location": "L145"}, {"caller_nid": "route_post", "callee": "filterSubmissionDataForUser", "source_file": "C:\\Users\\anton\\Documents\\Projects\\formflow\\formflow\\src\\app\\api\\submissions\\route.ts", "source_location": "L149"}, {"caller_nid": "route_post", "callee": "apiErrorResponse", "source_file": "C:\\Users\\anton\\Documents\\Projects\\formflow\\formflow\\src\\app\\api\\submissions\\route.ts", "source_location": "L160"}]}